oam_dl-0.2.1.dist-info/DESCRIPTION.rst
oam_dl-0.2.1.dist-info/METADATA
oam_dl-0.2.1.dist-info/RECORD
oam_dl-0.2.1.dist-info/WHEEL
oam_dl-0.2.1.dist-info/entry_points.txt
oam_dl-0.2.1.dist-info/metadata.json
oam_dl-0.2.1.dist-info/top_level.txt
oamdl/__init__.py
