Metadata-Version: 2.0
Name: oam-dl
Version: 0.2.1
Summary: Download any or all Ozy and Millie comics
Home-page: https://github.com/lethargilistic/oam-dl
Author: Mike Overby
Author-email: mikeoverby@outlook.com
License: MIT
Keywords: cli,commandline,download,api
Platform: UNKNOWN
Classifier: Intended Audience :: Developers
Classifier: Topic :: Software Development :: Build Tools
Classifier: License :: OSI Approved :: MIT License
Classifier: Environment :: Console
Classifier: Natural Language :: English
Classifier: Programming Language :: Python
Classifier: Programming Language :: Python :: 3
Classifier: Programming Language :: Python :: 3.4
Requires-Dist: docopt (==0.6.2)
Requires-Dist: progress (==1.2)
Requires-Dist: requests (==2.8.1)
Requires-Dist: wheel (==0.26.0)
